pyTitration/__init__.py
pyTitration/gui_calculator.py
pyTitration/k_values.py
pyTitration/titration.py
pyTitration-0.0.1.dist-info/LICENSE
pyTitration-0.0.1.dist-info/METADATA
pyTitration-0.0.1.dist-info/WHEEL
pyTitration-0.0.1.dist-info/top_level.txt
pyTitration-0.0.1.dist-info/RECORD
