Metadata-Version: 2.1
Name: pyTitration
Version: 0.0.1
Summary: For calculation of titration curves of solutions
Home-page: https://github.com/AlexanderSouthan/pyTitration
Author: Alexander Southan
Author-email: alexander.southan@web.de
Project-URL: Homepage, https://github.com/AlexanderSouthan/pyTitration
Project-URL: Bug Tracker, https://github.com/AlexanderSouthan/pyTitration/issues
Classifier: Programming Language :: Python :: 3
Classifier: License :: OSI Approved :: MIT License
Classifier: Operating System :: OS Independent
Requires-Python: >=3.7
License-File: LICENSE
Requires-Dist: numpy
Requires-Dist: pandas
Requires-Dist: matplotlib
Requires-Dist: sympy
Requires-Dist: pip
Requires-Dist: little-helpers
